dagster_ge/__init__.py
dagster_ge/factory.py
dagster_ge/version.py
dagster_ge-1.0.5.dist-info/LICENSE
dagster_ge-1.0.5.dist-info/METADATA
dagster_ge-1.0.5.dist-info/WHEEL
dagster_ge-1.0.5.dist-info/top_level.txt
dagster_ge-1.0.5.dist-info/RECORD
