Metadata-Version: 2.1
Name: dagster-ge
Version: 1.0.5
Summary: Package for GE-specific Dagster framework op and resource components.
Home-page: https://github.com/dagster-io/dagster/tree/master/python_modules/libraries/dagster-ge
Author: Elementl
License: Apache-2.0
Platform: UNKNOWN
Classifier: Programming Language :: Python :: 3.7
Classifier: Programming Language :: Python :: 3.8
Classifier: Programming Language :: Python :: 3.9
Classifier: License :: OSI Approved :: Apache Software License
Classifier: Operating System :: OS Independent
License-File: LICENSE
Requires-Dist: dagster (==1.0.5)
Requires-Dist: dagster-pandas (==1.0.5)
Requires-Dist: pandas
Requires-Dist: great-expectations (!=0.12.8,!=0.13.17,!=0.13.27,>=0.11.9)
